LICENSE
README.md
pyproject.toml
setup.py
test/test_Constellation.py
test/test_Direction.py
test/test_DogDay.py
test/test_Duty.py
test/test_EarthBranch.py
test/test_Ecliptic.py
test/test_Eightchar.py
test/test_Element.py
test/test_Fetus.py
test/test_God.py
test/test_HeavenStem.py
test/test_HideHeavenStem.py
test/test_JulianDay.py
test/test_LegalHoliday.py
test/test_LunarDay.py
test/test_LunarFestival.py
test/test_LunarHour.py
test/test_LunarMonth.py
test/test_LunarYear.py
test/test_NineDay.py
test/test_NineStar.py
test/test_Phase.py
test/test_Phenology.py
test/test_PlumRainDay.py
test/test_RabByungDay.py
test/test_RabByungMonth.py
test/test_RabByungYear.py
test/test_SixStar.py
test/test_Sixtycycle.py
test/test_SolarDay.py
test/test_SolarFestival.py
test/test_SolarHalfYear.py
test/test_SolarMonth.py
test/test_SolarSeason.py
test/test_SolarTerm.py
test/test_SolarTime.py
test/test_SolarYear.py
test/test_Taboo.py
test/test_ThreePillars.py
test/test_Week.py
tyme4py/__init__.py
tyme4py.egg-info/PKG-INFO
tyme4py.egg-info/SOURCES.txt
tyme4py.egg-info/dependency_links.txt
tyme4py.egg-info/requires.txt
tyme4py.egg-info/top_level.txt
tyme4py/culture/__init__.py
tyme4py/culture/dog/__init__.py
tyme4py/culture/fetus/__init__.py
tyme4py/culture/nine/__init__.py
tyme4py/culture/pengzu/__init__.py
tyme4py/culture/phenology/__init__.py
tyme4py/culture/plumrain/__init__.py
tyme4py/culture/ren/__init__.py
tyme4py/culture/star/__init__.py
tyme4py/culture/star/nine.py
tyme4py/culture/star/seven.py
tyme4py/culture/star/six.py
tyme4py/culture/star/ten.py
tyme4py/culture/star/twelve.py
tyme4py/culture/star/twentyeight.py
tyme4py/eightchar/__init__.py
tyme4py/eightchar/provider/__init__.py
tyme4py/eightchar/provider/impl/__init__.py
tyme4py/enums/__init__.py
tyme4py/festival/__init__.py
tyme4py/holiday/__init__.py
tyme4py/jd/__init__.py
tyme4py/lunar/__init__.py
tyme4py/rabbyung/__init__.py
tyme4py/sixtycycle/__init__.py
tyme4py/solar/__init__.py
tyme4py/unit/__init__.py
tyme4py/util/__init__.py