Metadata-Version: 2.4
Name: tyme4py
Version: 1.4.3
Summary: Tyme是一个非常强大的日历工具库，可以看作 Lunar 的升级版，拥有更优的设计和扩展性，支持公历、农历、藏历、星座、干支、生肖、节气、法定假日等。
Home-page: https://github.com/6tail/tyme4py
Author: 6tail
Author-email: 6tail <6tail@6tail.cn>
License: MIT License
Keywords: 公历,农历,藏历,儒略日,星座,干支,节气,法定假日
Requires-Python: >=3.10
License-File: LICENSE
Requires-Dist: setuptools>=80.9.0
Dynamic: author
Dynamic: home-page
Dynamic: license-file
Dynamic: requires-python
